{
  "eui.button.border.width": {
    "$value": "1px",
    "$type": "dimension"
  },
  "eui.button.border.style": {
    "$value": "solid",
    "$type": "string"
  },
  "eui.button.states.hover": {
    "$value": "emphasize",
    "$type": "stateEffect"
  },
  "eui.button.states.active": {
    "$value": "press",
    "$type": "stateEffect"
  },
  "eui.button.states.disabled": {
    "$value": "mute",
    "$type": "stateEffect"
  },
  "eui.button.states.selected": {
    "$value": "select",
    "$type": "stateEffect"
  },
  "eui.button.primary.background.base": {
    "$value": "#066a8d",
    "$type": "color"
  },
  "eui.button.primary.background.hover": {
    "$value": "#066a8d",
    "$type": "color"
  },
  "eui.button.primary.background.active": {
    "$value": "#066a8d",
    "$type": "color"
  },
  "eui.button.primary.background.disabled": {
    "$value": "#e5e7eb",
    "$type": "color"
  },
  "eui.button.primary.background.selected": {
    "$value": "#066a8d",
    "$type": "color"
  },
  "eui.button.primary.label.base": {
    "$value": "#ffffff",
    "$type": "color"
  },
  "eui.button.primary.label.hover": {
    "$value": "#ffffff",
    "$type": "color"
  },
  "eui.button.primary.label.active": {
    "$value": "#ffffff",
    "$type": "color"
  },
  "eui.button.primary.label.disabled": {
    "$value": "#404040",
    "$type": "color"
  },
  "eui.button.primary.label.selected": {
    "$value": "#ffffff",
    "$type": "color"
  },
  "eui.button.secondary.background.base": {
    "$value": "#ffffff",
    "$type": "color"
  },
  "eui.button.secondary.background.hover": {
    "$value": "#ffffff",
    "$type": "color"
  },
  "eui.button.secondary.background.active": {
    "$value": "#ffffff",
    "$type": "color"
  },
  "eui.button.secondary.background.disabled": {
    "$value": "#e5e7eb",
    "$type": "color"
  },
  "eui.button.secondary.background.selected": {
    "$value": "#ffffff",
    "$type": "color"
  },
  "eui.button.secondary.label.base": {
    "$value": "#1b1b1b",
    "$type": "color"
  },
  "eui.button.secondary.label.hover": {
    "$value": "#1b1b1b",
    "$type": "color"
  },
  "eui.button.secondary.label.active": {
    "$value": "#1b1b1b",
    "$type": "color"
  },
  "eui.button.secondary.label.disabled": {
    "$value": "#404040",
    "$type": "color"
  },
  "eui.button.secondary.label.selected": {
    "$value": "#1b1b1b",
    "$type": "color"
  },
  "eui.button.secondary.border.base": {
    "$value": "#525252",
    "$type": "color"
  },
  "eui.button.secondary.border.hover": {
    "$value": "#525252",
    "$type": "color"
  },
  "eui.button.secondary.border.active": {
    "$value": "#525252",
    "$type": "color"
  },
  "eui.button.secondary.border.disabled": {
    "$value": "#525252",
    "$type": "color"
  },
  "eui.button.secondary.border.selected": {
    "$value": "#525252",
    "$type": "color"
  },
  "eui.button.accent.background.base": {
    "$value": "#2d98e8",
    "$type": "color"
  },
  "eui.button.accent.background.hover": {
    "$value": "#2d98e8",
    "$type": "color"
  },
  "eui.button.accent.background.active": {
    "$value": "#2d98e8",
    "$type": "color"
  },
  "eui.button.accent.background.disabled": {
    "$value": "#e5e7eb",
    "$type": "color"
  },
  "eui.button.accent.background.selected": {
    "$value": "#2d98e8",
    "$type": "color"
  },
  "eui.button.accent.label.base": {
    "$value": "#ffffff",
    "$type": "color"
  },
  "eui.button.accent.label.hover": {
    "$value": "#ffffff",
    "$type": "color"
  },
  "eui.button.accent.label.active": {
    "$value": "#ffffff",
    "$type": "color"
  },
  "eui.button.accent.label.disabled": {
    "$value": "#404040",
    "$type": "color"
  },
  "eui.button.accent.label.selected": {
    "$value": "#ffffff",
    "$type": "color"
  },
  "eui.button.focus.ring.color.derived": {
    "$value": "#066a8d",
    "$type": "color"
  },
  "eui.button.focus.ring.width.base": {
    "$value": "2px",
    "$type": "dimension"
  },
  "eui.button.focus.ring.width.accessible": {
    "$value": "3px",
    "$type": "dimension"
  },
  "eui.button.focus.ring.offset.base": {
    "$value": "0px",
    "$type": "dimension"
  },
  "eui.button.group.orientation.horizontal": {
    "$value": "horizontal",
    "$type": "string"
  },
  "eui.button.group.orientation.vertical": {
    "$value": "vertical",
    "$type": "string"
  },
  "eui.button.group.position.single.shape.corner.topLeft": {
    "$value": "4px",
    "$type": "dimension"
  },
  "eui.button.group.position.single.shape.corner.topRight": {
    "$value": "4px",
    "$type": "dimension"
  },
  "eui.button.group.position.single.shape.corner.bottomRight": {
    "$value": "4px",
    "$type": "dimension"
  },
  "eui.button.group.position.single.shape.corner.bottomLeft": {
    "$value": "4px",
    "$type": "dimension"
  },
  "eui.button.group.position.first.shape.orientation.horizontal.corner.topLeft": {
    "$value": "4px",
    "$type": "dimension"
  },
  "eui.button.group.position.first.shape.orientation.horizontal.corner.topRight": {
    "$value": "0px",
    "$type": "dimension"
  },
  "eui.button.group.position.first.shape.orientation.horizontal.corner.bottomRight": {
    "$value": "0px",
    "$type": "dimension"
  },
  "eui.button.group.position.first.shape.orientation.horizontal.corner.bottomLeft": {
    "$value": "4px",
    "$type": "dimension"
  },
  "eui.button.group.position.first.shape.orientation.vertical.corner.topLeft": {
    "$value": "4px",
    "$type": "dimension"
  },
  "eui.button.group.position.first.shape.orientation.vertical.corner.topRight": {
    "$value": "4px",
    "$type": "dimension"
  },
  "eui.button.group.position.first.shape.orientation.vertical.corner.bottomRight": {
    "$value": "0px",
    "$type": "dimension"
  },
  "eui.button.group.position.first.shape.orientation.vertical.corner.bottomLeft": {
    "$value": "0px",
    "$type": "dimension"
  },
  "eui.button.group.position.middle.shape.orientation.horizontal.corner.topLeft": {
    "$value": "0px",
    "$type": "dimension"
  },
  "eui.button.group.position.middle.shape.orientation.horizontal.corner.topRight": {
    "$value": "0px",
    "$type": "dimension"
  },
  "eui.button.group.position.middle.shape.orientation.horizontal.corner.bottomRight": {
    "$value": "0px",
    "$type": "dimension"
  },
  "eui.button.group.position.middle.shape.orientation.horizontal.corner.bottomLeft": {
    "$value": "0px",
    "$type": "dimension"
  },
  "eui.button.group.position.middle.shape.orientation.vertical.corner.topLeft": {
    "$value": "0px",
    "$type": "dimension"
  },
  "eui.button.group.position.middle.shape.orientation.vertical.corner.topRight": {
    "$value": "0px",
    "$type": "dimension"
  },
  "eui.button.group.position.middle.shape.orientation.vertical.corner.bottomRight": {
    "$value": "0px",
    "$type": "dimension"
  },
  "eui.button.group.position.middle.shape.orientation.vertical.corner.bottomLeft": {
    "$value": "0px",
    "$type": "dimension"
  },
  "eui.button.group.position.last.shape.orientation.horizontal.corner.topLeft": {
    "$value": "0px",
    "$type": "dimension"
  },
  "eui.button.group.position.last.shape.orientation.horizontal.corner.topRight": {
    "$value": "4px",
    "$type": "dimension"
  },
  "eui.button.group.position.last.shape.orientation.horizontal.corner.bottomRight": {
    "$value": "4px",
    "$type": "dimension"
  },
  "eui.button.group.position.last.shape.orientation.horizontal.corner.bottomLeft": {
    "$value": "0px",
    "$type": "dimension"
  },
  "eui.button.group.position.last.shape.orientation.vertical.corner.topLeft": {
    "$value": "0px",
    "$type": "dimension"
  },
  "eui.button.group.position.last.shape.orientation.vertical.corner.topRight": {
    "$value": "0px",
    "$type": "dimension"
  },
  "eui.button.group.position.last.shape.orientation.vertical.corner.bottomRight": {
    "$value": "4px",
    "$type": "dimension"
  },
  "eui.button.group.position.last.shape.orientation.vertical.corner.bottomLeft": {
    "$value": "4px",
    "$type": "dimension"
  },
  "eui.button.layout.stack.internalBorder.horizontal": {
    "$value": "none",
    "$type": "string"
  },
  "eui.button.layout.stack.internalBorder.vertical": {
    "$value": "none",
    "$type": "string"
  },
  "eui.button.layout.stack.perimeterBorder": {
    "$value": "preserve",
    "$type": "string"
  },
  "eui.button.layout.stack.separator.inset": {
    "$value": "6px",
    "$type": "dimension"
  },
  "eui.button.layout.stack.separator.thickness": {
    "$value": "1px",
    "$type": "dimension"
  },
  "eui.button.layout.default.flex.grow": {
    "$value": "0",
    "$type": "string"
  },
  "eui.button.layout.default.flex.shrink": {
    "$value": "0",
    "$type": "string"
  },
  "eui.button.layout.default.flex.basis": {
    "$value": "auto",
    "$type": "string"
  },
  "eui.button.layout.default.whiteSpace": {
    "$value": "nowrap",
    "$type": "string"
  },
  "eui.button.separator.inset": {
    "$value": "6px",
    "$type": "dimension"
  },
  "eui.button.separator.thickness": {
    "$value": "1px",
    "$type": "dimension"
  },
  "eui.button.shape.default.radius": {
    "$value": "4px",
    "$type": "dimension"
  },
  "eui.button.shape.round.radius": {
    "$value": "999px",
    "$type": "dimension"
  },
  "eui.button.shape.circle.radius": {
    "$value": "50%",
    "$type": "dimension"
  },
  "eui.button.size.sm.height": {
    "$value": "36px",
    "$type": "dimension"
  },
  "eui.button.size.sm.padding.inline": {
    "$value": "16px",
    "$type": "dimension"
  },
  "eui.button.size.sm.font.size": {
    "$value": "0.9rem",
    "$type": "fontSize"
  },
  "eui.button.size.sm.font.weight": {
    "$value": "600",
    "$type": "fontWeight"
  },
  "eui.button.size.sm.gap": {
    "$value": "0.35rem",
    "$type": "dimension"
  },
  "eui.button.size.md.height": {
    "$value": "40px",
    "$type": "dimension"
  },
  "eui.button.size.md.padding.inline": {
    "$value": "20px",
    "$type": "dimension"
  },
  "eui.button.size.md.font.size": {
    "$value": "0.95rem",
    "$type": "fontSize"
  },
  "eui.button.size.md.font.weight": {
    "$value": "600",
    "$type": "fontWeight"
  },
  "eui.button.size.md.gap": {
    "$value": "0.4rem",
    "$type": "dimension"
  },
  "eui.button.size.lg.height": {
    "$value": "48px",
    "$type": "dimension"
  },
  "eui.button.size.lg.padding.inline": {
    "$value": "24px",
    "$type": "dimension"
  },
  "eui.button.size.lg.font.size": {
    "$value": "1rem",
    "$type": "fontSize"
  },
  "eui.button.size.lg.font.weight": {
    "$value": "600",
    "$type": "fontWeight"
  },
  "eui.button.size.lg.gap": {
    "$value": "0.45rem",
    "$type": "dimension"
  },
  "eui.color.accent.50": {
    "$value": "#f1f8ff",
    "$type": "color"
  },
  "eui.color.accent.100": {
    "$value": "#dceeff",
    "$type": "color"
  },
  "eui.color.accent.200": {
    "$value": "#b7dbff",
    "$type": "color"
  },
  "eui.color.accent.300": {
    "$value": "#8ac4ff",
    "$type": "color"
  },
  "eui.color.accent.400": {
    "$value": "#55a7ff",
    "$type": "color"
  },
  "eui.color.accent.500": {
    "$value": "#3db0ff",
    "$type": "color"
  },
  "eui.color.accent.600": {
    "$value": "#35a8f8",
    "$type": "color"
  },
  "eui.color.accent.700": {
    "$value": "#2d98e8",
    "$type": "color"
  },
  "eui.color.accent.800": {
    "$value": "#2588d8",
    "$type": "color"
  },
  "eui.color.accent.900": {
    "$value": "#1e78c8",
    "$type": "color"
  },
  "eui.color.accent.primary": {
    "$value": "#2d98e8",
    "$type": "color"
  },
  "eui.color.brand.50": {
    "$value": "#e6f6fb",
    "$type": "color"
  },
  "eui.color.brand.100": {
    "$value": "#c9edf7",
    "$type": "color"
  },
  "eui.color.brand.200": {
    "$value": "#9ad8ee",
    "$type": "color"
  },
  "eui.color.brand.300": {
    "$value": "#63c0e2",
    "$type": "color"
  },
  "eui.color.brand.400": {
    "$value": "#2ea7d1",
    "$type": "color"
  },
  "eui.color.brand.500": {
    "$value": "#007fa2",
    "$type": "color"
  },
  "eui.color.brand.600": {
    "$value": "#007ca0",
    "$type": "color"
  },
  "eui.color.brand.700": {
    "$value": "#066a8d",
    "$type": "color"
  },
  "eui.color.brand.800": {
    "$value": "#055973",
    "$type": "color"
  },
  "eui.color.brand.900": {
    "$value": "#043c55",
    "$type": "color"
  },
  "eui.color.brand.primary": {
    "$value": "#066a8d",
    "$type": "color"
  },
  "eui.color.neutral.50": {
    "$value": "#f8fafc",
    "$type": "color"
  },
  "eui.color.neutral.100": {
    "$value": "#f1f2f7",
    "$type": "color"
  },
  "eui.color.neutral.200": {
    "$value": "#e5e7eb",
    "$type": "color"
  },
  "eui.color.neutral.300": {
    "$value": "#cccccc",
    "$type": "color"
  },
  "eui.color.neutral.400": {
    "$value": "#a3a3a3",
    "$type": "color"
  },
  "eui.color.neutral.500": {
    "$value": "#757575",
    "$type": "color"
  },
  "eui.color.neutral.600": {
    "$value": "#525252",
    "$type": "color"
  },
  "eui.color.neutral.700": {
    "$value": "#404040",
    "$type": "color"
  },
  "eui.color.neutral.800": {
    "$value": "#262626",
    "$type": "color"
  },
  "eui.color.neutral.900": {
    "$value": "#1b1b1b",
    "$type": "color"
  },
  "eui.color.neutral.white": {
    "$value": "#ffffff",
    "$type": "color"
  },
  "eui.color.signal.keyboardFocus": {
    "$value": "#ff4d00",
    "$type": "color",
    "$description": "Keyboard-only focus ring (a11y)"
  },
  "eui.color.status.success": {
    "$value": "#22c55e",
    "$type": "color"
  },
  "eui.color.status.warning": {
    "$value": "#f59e0b",
    "$type": "color"
  },
  "eui.color.status.error": {
    "$value": "#ef4444",
    "$type": "color"
  },
  "eui.color.status.info": {
    "$value": "#0ea5e9",
    "$type": "color"
  },
  "eui.color.background.surface": {
    "$value": "#ffffff",
    "$type": "color"
  },
  "eui.color.background.muted": {
    "$value": "#e5e7eb",
    "$type": "color"
  },
  "eui.color.background.subtle": {
    "$value": "#f1f2f7",
    "$type": "color"
  },
  "eui.color.background.inverse": {
    "$value": "#1b1b1b",
    "$type": "color"
  },
  "eui.color.border.default": {
    "$value": "#525252",
    "$type": "color"
  },
  "eui.color.border.subtle": {
    "$value": "#e5e7eb",
    "$type": "color"
  },
  "eui.color.border.strong": {
    "$value": "#a3a3a3",
    "$type": "color"
  },
  "eui.color.border.inverse": {
    "$value": "#262626",
    "$type": "color"
  },
  "eui.color.focus.ring": {
    "$value": "#ff4d00",
    "$type": "color"
  },
  "eui.color.system.focus": {
    "$value": "#ff4d00",
    "$type": "color"
  },
  "eui.color.text.primary": {
    "$value": "#1b1b1b",
    "$type": "color"
  },
  "eui.color.text.muted": {
    "$value": "#404040",
    "$type": "color"
  },
  "eui.color.text.subtle": {
    "$value": "#525252",
    "$type": "color"
  },
  "eui.color.text.inverse": {
    "$value": "#ffffff",
    "$type": "color"
  },
  "eui.color.text.disabled": {
    "$value": "#404040",
    "$type": "color"
  },
  "eui.radius.pill": {
    "$value": "999px",
    "$type": "dimension"
  },
  "eui.radius.none": {
    "$value": "0px",
    "$type": "dimension"
  },
  "eui.radius.small": {
    "$value": "2px",
    "$type": "dimension"
  },
  "eui.radius.default": {
    "$value": "4px",
    "$type": "dimension"
  },
  "eui.radius.large": {
    "$value": "4px",
    "$type": "dimension"
  },
  "eui.radius.extra-large": {
    "$value": "6px",
    "$type": "dimension"
  },
  "eui.radius.full": {
    "$value": "999px",
    "$type": "dimension"
  },
  "eui.focus.ring.width.base": {
    "$value": "2px",
    "$type": "dimension"
  },
  "eui.focus.ring.width.accessible": {
    "$value": "3px",
    "$type": "dimension"
  }
}